{
  "setting_0": {
    "batch_size": 128.0,
    "microbatch_size": 1,
    "test_batch_size": 1000,
    "iterations": 5000,
    "learning_rate": 0.001,
    "gamma": 0.9,
    "no_cuda": false,
    "dry_run": false,
    "seed": 1,
    "log_interval": 10,
    "save_model": false,
    "noise_multiplier": 0.4,
    "max_grad_norm": 1.2,
    "optimizer": "SGD",
    "enable_DP": true,
    "diminishing_gradient_norm": false,
    "is_individual_clipping": true,
    "data_sampling": "subsampling",
    "train_accuracy": [
      0.10000000149011612,
      0.10026666522026062,
      0.09902222454547882,
      0.10273333638906479,
      0.10082222521305084,
      0.10202222317457199,
      0.10282222181558609,
      0.10091111063957214,
      0.0981111153960228,
      0.10037777572870255
    ],
    "test_accuracy": [
      0.09999999403953552,
      0.09989999979734421,
      0.09999999403953552,
      0.09999999403953552,
      0.10009999573230743,
      0.10019999742507935,
      0.10009999573230743,
      0.10019999742507935,
      0.10040000081062317,
      0.10009999573230743
    ],
    "model_name": "convnet"
  },
  "setting_1": {
    "batch_size": 64.0,
    "microbatch_size": 64,
    "test_batch_size": 1000,
    "iterations": 10000,
    "learning_rate": 0.025,
    "gamma": 0.9,
    "no_cuda": false,
    "dry_run": false,
    "seed": 1,
    "log_interval": 10,
    "save_model": false,
    "noise_multiplier": 2.0,
    "max_grad_norm": 0.18,
    "optimizer": "SGD",
    "enable_DP": true,
    "diminishing_gradient_norm": false,
    "is_individual_clipping": false,
    "data_sampling": "subsampling",
    "train_accuracy": [
      0.11168888956308365,
      0.1253555566072464,
      0.11962222307920456,
      0.13377778232097626,
      0.1279333382844925,
      0.14144444465637207,
      0.14633333683013916,
      0.15764445066452026,
      0.17382222414016724,
      0.18431110680103302
    ],
    "test_accuracy": [
      0.11319999396800995,
      0.1225999966263771,
      0.11899999529123306,
      0.12960000336170197,
      0.12999999523162842,
      0.1378999948501587,
      0.14919999241828918,
      0.16099999845027924,
      0.17679999768733978,
      0.18389999866485596
    ],
    "model_name": "convnet"
  },
  "setting_2": {
    "batch_size": 128.0,
    "microbatch_size": 64,
    "test_batch_size": 1000,
    "iterations": 10000,
    "learning_rate": 0.025,
    "gamma": 0.9,
    "no_cuda": false,
    "dry_run": false,
    "seed": 1,
    "log_interval": 10,
    "save_model": false,
    "noise_multiplier": 2.0,
    "max_grad_norm": 0.18,
    "optimizer": "SGD",
    "enable_DP": true,
    "diminishing_gradient_norm": false,
    "is_individual_clipping": false,
    "data_sampling": "subsampling",
    "train_accuracy": [
      0.18364444375038147,
      0.18157778680324554,
      0.1790444403886795,
      0.17499999701976776,
      0.17697778344154358,
      0.17642222344875336,
      0.1751333326101303,
      0.17982222139835358,
      0.18000000715255737,
      0.17888888716697693
    ],
    "test_accuracy": [
      0.18320000171661377,
      0.18299999833106995,
      0.18209999799728394,
      0.17759999632835388,
      0.17949999868869781,
      0.17409999668598175,
      0.17589999735355377,
      0.1777999997138977,
      0.17829999327659607,
      0.17589999735355377
    ],
    "model_name": "convnet"
  },
  "setting_3": {
    "batch_size": 256.0,
    "microbatch_size": 64,
    "test_batch_size": 1000,
    "iterations": 10000,
    "learning_rate": 0.025,
    "gamma": 0.9,
    "no_cuda": false,
    "dry_run": false,
    "seed": 1,
    "log_interval": 10,
    "save_model": false,
    "noise_multiplier": 2.0,
    "max_grad_norm": 0.18,
    "optimizer": "SGD",
    "enable_DP": true,
    "diminishing_gradient_norm": false,
    "is_individual_clipping": false,
    "data_sampling": "subsampling",
    "train_accuracy": [
      0.17746667563915253,
      0.17599999904632568,
      0.1759333312511444,
      0.1788666695356369,
      0.17740000784397125,
      0.1724444478750229,
      0.17133332788944244,
      0.17571111023426056,
      0.17331111431121826,
      0.1763777732849121
    ],
    "test_accuracy": [
      0.17989999055862427,
      0.17659999430179596,
      0.17419999837875366,
      0.17339999973773956,
      0.17809998989105225,
      0.17549999058246613,
      0.17599999904632568,
      0.17219999432563782,
      0.17139999568462372,
      0.17759999632835388
    ],
    "model_name": "convnet"
  },
  "setting_4": {
    "batch_size": 512.0,
    "microbatch_size": 64,
    "test_batch_size": 1000,
    "iterations": 10000,
    "learning_rate": 0.025,
    "gamma": 0.9,
    "no_cuda": false,
    "dry_run": false,
    "seed": 1,
    "log_interval": 10,
    "save_model": false,
    "noise_multiplier": 2.0,
    "max_grad_norm": 0.18,
    "optimizer": "SGD",
    "enable_DP": true,
    "diminishing_gradient_norm": false,
    "is_individual_clipping": false,
    "data_sampling": "subsampling",
    "train_accuracy": [
      0.1754888892173767,
      0.17248889803886414,
      0.17180000245571136,
      0.17204444110393524,
      0.1758444458246231,
      0.17640000581741333,
      0.1744888871908188,
      0.1738000065088272,
      0.1730888932943344,
      0.17657777667045593
    ],
    "test_accuracy": [
      0.17109999060630798,
      0.17319999635219574,
      0.1753000020980835,
      0.16990000009536743,
      0.17599999904632568,
      0.17679999768733978,
      0.17019999027252197,
      0.17289999127388,
      0.17379999160766602,
      0.17679999768733978
    ],
    "model_name": "convnet"
  },
  "setting_5": {
    "batch_size": 1024.0,
    "microbatch_size": 64,
    "test_batch_size": 1000,
    "iterations": 10000,
    "learning_rate": 0.025,
    "gamma": 0.9,
    "no_cuda": false,
    "dry_run": false,
    "seed": 1,
    "log_interval": 10,
    "save_model": false,
    "noise_multiplier": 2.0,
    "max_grad_norm": 0.18,
    "optimizer": "SGD",
    "enable_DP": true,
    "diminishing_gradient_norm": false,
    "is_individual_clipping": false,
    "data_sampling": "subsampling",
    "train_accuracy": [
      0.17437778413295746,
      0.17484444379806519,
      0.17366667091846466,
      0.17373333871364594,
      0.1733555644750595,
      0.17615555226802826,
      0.176822230219841,
      0.17017777264118195,
      0.17408889532089233,
      0.17322222888469696
    ],
    "test_accuracy": [
      0.17309999465942383,
      0.1744999885559082,
      0.17809998989105225,
      0.17289999127388,
      0.17649999260902405,
      0.1720999926328659,
      0.1736999899148941,
      0.17339999973773956,
      0.17799998819828033,
      0.1753000020980835
    ],
    "model_name": "convnet"
  },
  "setting_6": {
    "batch_size": 64.0,
    "microbatch_size": 64,
    "test_batch_size": 1000,
    "iterations": 10000,
    "learning_rate": 0.025,
    "gamma": 0.9,
    "no_cuda": false,
    "dry_run": false,
    "seed": 1,
    "log_interval": 10,
    "save_model": false,
    "noise_multiplier": 2.0,
    "max_grad_norm": 0.36,
    "optimizer": "SGD",
    "enable_DP": true,
    "diminishing_gradient_norm": false,
    "is_individual_clipping": false,
    "data_sampling": "subsampling",
    "train_accuracy": [
      0.16546666622161865,
      0.1812666654586792,
      0.18648889660835266,
      0.18815556168556213,
      0.19066667556762695,
      0.1946222186088562,
      0.20168888568878174,
      0.2065555602312088,
      0.20837777853012085,
      0.20357778668403625
    ],
    "test_accuracy": [
      0.17069999873638153,
      0.18479999899864197,
      0.18859998881816864,
      0.19209998846054077,
      0.19589999318122864,
      0.19579999148845673,
      0.20799998939037323,
      0.21239998936653137,
      0.2094999998807907,
      0.21139998733997345
    ],
    "model_name": "convnet"
  },
  "setting_7": {
    "batch_size": 128.0,
    "microbatch_size": 64,
    "test_batch_size": 1000,
    "iterations": 10000,
    "learning_rate": 0.025,
    "gamma": 0.9,
    "no_cuda": false,
    "dry_run": false,
    "seed": 1,
    "log_interval": 10,
    "save_model": false,
    "noise_multiplier": 2.0,
    "max_grad_norm": 0.36,
    "optimizer": "SGD",
    "enable_DP": true,
    "diminishing_gradient_norm": false,
    "is_individual_clipping": false,
    "data_sampling": "subsampling",
    "train_accuracy": [
      0.19073332846164703,
      0.19166666269302368,
      0.19566667079925537,
      0.2033555507659912,
      0.20280000567436218,
      0.209933340549469,
      0.20268888771533966,
      0.20608888566493988,
      0.20464444160461426,
      0.20902222394943237
    ],
    "test_accuracy": [
      0.19460000097751617,
      0.19939999282360077,
      0.20250000059604645,
      0.20960000157356262,
      0.2125999927520752,
      0.21459999680519104,
      0.2102999985218048,
      0.2142999917268753,
      0.21079999208450317,
      0.21459999680519104
    ],
    "model_name": "convnet"
  },
  "setting_8": {
    "batch_size": 256.0,
    "microbatch_size": 64,
    "test_batch_size": 1000,
    "iterations": 10000,
    "learning_rate": 0.025,
    "gamma": 0.9,
    "no_cuda": false,
    "dry_run": false,
    "seed": 1,
    "log_interval": 10,
    "save_model": false,
    "noise_multiplier": 2.0,
    "max_grad_norm": 0.36,
    "optimizer": "SGD",
    "enable_DP": true,
    "diminishing_gradient_norm": false,
    "is_individual_clipping": false,
    "data_sampling": "subsampling",
    "train_accuracy": [
      0.2062888890504837,
      0.20242223143577576,
      0.20871111750602722,
      0.21142221987247467,
      0.20662222802639008,
      0.21395555138587952,
      0.21533334255218506,
      0.21160000562667847,
      0.21613334119319916,
      0.21004444360733032
    ],
    "test_accuracy": [
      0.21139998733997345,
      0.2101999968290329,
      0.21549999713897705,
      0.21619999408721924,
      0.21490000188350677,
      0.22209998965263367,
      0.21979999542236328,
      0.21969999372959137,
      0.21939998865127563,
      0.22109998762607574
    ],
    "model_name": "convnet"
  },
  "setting_9": {
    "batch_size": 512.0,
    "microbatch_size": 64,
    "test_batch_size": 1000,
    "iterations": 10000,
    "learning_rate": 0.025,
    "gamma": 0.9,
    "no_cuda": false,
    "dry_run": false,
    "seed": 1,
    "log_interval": 10,
    "save_model": false,
    "noise_multiplier": 2.0,
    "max_grad_norm": 0.36,
    "optimizer": "SGD",
    "enable_DP": true,
    "diminishing_gradient_norm": false,
    "is_individual_clipping": false,
    "data_sampling": "subsampling",
    "train_accuracy": [
      0.2157333344221115,
      0.21373333036899567,
      0.2132444530725479,
      0.2135777771472931,
      0.21526667475700378,
      0.21417778730392456,
      0.2160888910293579,
      0.2150222212076187,
      0.21539999544620514,
      0.2174222320318222
    ],
    "test_accuracy": [
      0.2198999971151352,
      0.22129999101161957,
      0.2207999974489212,
      0.21879999339580536,
      0.22019998729228973,
      0.21819999814033508,
      0.21889999508857727,
      0.22109998762607574,
      0.21899999678134918,
      0.2256999909877777
    ],
    "model_name": "convnet"
  },
  "setting_10": {
    "batch_size": 1024.0,
    "microbatch_size": 64,
    "test_batch_size": 1000,
    "iterations": 10000,
    "learning_rate": 0.025,
    "gamma": 0.9,
    "no_cuda": false,
    "dry_run": false,
    "seed": 1,
    "log_interval": 10,
    "save_model": false,
    "noise_multiplier": 2.0,
    "max_grad_norm": 0.36,
    "optimizer": "SGD",
    "enable_DP": true,
    "diminishing_gradient_norm": false,
    "is_individual_clipping": false,
    "data_sampling": "subsampling",
    "train_accuracy": [
      0.21888889372348785,
      0.21684443950653076,
      0.21762222051620483,
      0.21495555341243744,
      0.21806666254997253,
      0.21511110663414001,
      0.21431110799312592,
      0.21693333983421326,
      0.21391111612319946,
      0.2144000083208084
    ],
    "test_accuracy": [
      0.2224999964237213,
      0.2255999892950058,
      0.22039999067783356,
      0.21969999372959137,
      0.22289998829364777,
      0.22019998729228973,
      0.2198999971151352,
      0.22129999101161957,
      0.2199999988079071,
      0.22259999811649323
    ],
    "model_name": "convnet"
  },
  "setting_11": {
    "batch_size": 64.0,
    "microbatch_size": 64,
    "test_batch_size": 1000,
    "iterations": 10000,
    "learning_rate": 0.025,
    "gamma": 0.9,
    "no_cuda": false,
    "dry_run": false,
    "seed": 1,
    "log_interval": 10,
    "save_model": false,
    "noise_multiplier": 2.0,
    "max_grad_norm": 0.72,
    "optimizer": "SGD",
    "enable_DP": true,
    "diminishing_gradient_norm": false,
    "is_individual_clipping": false,
    "data_sampling": "subsampling",
    "train_accuracy": [
      0.21364444494247437,
      0.20766666531562805,
      0.2210666686296463,
      0.21700000762939453,
      0.21924445033073425,
      0.23651111125946045,
      0.2365555614233017,
      0.24140000343322754,
      0.2409111112356186,
      0.22777777910232544
    ],
    "test_accuracy": [
      0.22139999270439148,
      0.2133999913930893,
      0.23089998960494995,
      0.21949999034404755,
      0.22139999270439148,
      0.24639999866485596,
      0.23929999768733978,
      0.24899999797344208,
      0.24819999933242798,
      0.23539999127388
    ],
    "model_name": "convnet"
  },
  "setting_12": {
    "batch_size": 128.0,
    "microbatch_size": 64,
    "test_batch_size": 1000,
    "iterations": 10000,
    "learning_rate": 0.025,
    "gamma": 0.9,
    "no_cuda": false,
    "dry_run": false,
    "seed": 1,
    "log_interval": 10,
    "save_model": false,
    "noise_multiplier": 2.0,
    "max_grad_norm": 0.72,
    "optimizer": "SGD",
    "enable_DP": true,
    "diminishing_gradient_norm": false,
    "is_individual_clipping": false,
    "data_sampling": "subsampling",
    "train_accuracy": [
      0.2421555519104004,
      0.24542222917079926,
      0.23971112072467804,
      0.24199999868869781,
      0.24542222917079926,
      0.24953334033489227,
      0.2495555579662323,
      0.24675555527210236,
      0.24311111867427826,
      0.24491111934185028
    ],
    "test_accuracy": [
      0.2475999891757965,
      0.25459998846054077,
      0.2524999976158142,
      0.24569998681545258,
      0.2563999891281128,
      0.2532999813556671,
      0.25619998574256897,
      0.25040000677108765,
      0.24819999933242798,
      0.2467999905347824
    ],
    "model_name": "convnet"
  },
  "setting_13": {
    "batch_size": 256.0,
    "microbatch_size": 64,
    "test_batch_size": 1000,
    "iterations": 10000,
    "learning_rate": 0.025,
    "gamma": 0.9,
    "no_cuda": false,
    "dry_run": false,
    "seed": 1,
    "log_interval": 10,
    "save_model": false,
    "noise_multiplier": 2.0,
    "max_grad_norm": 0.72,
    "optimizer": "SGD",
    "enable_DP": true,
    "diminishing_gradient_norm": false,
    "is_individual_clipping": false,
    "data_sampling": "subsampling",
    "train_accuracy": [
      0.24979999661445618,
      0.2498222291469574,
      0.24553333222866058,
      0.25208890438079834,
      0.2447555512189865,
      0.24326667189598083,
      0.24568888545036316,
      0.24684444069862366,
      0.24782222509384155,
      0.24802222847938538
    ],
    "test_accuracy": [
      0.260699987411499,
      0.25949999690055847,
      0.2540999948978424,
      0.2554999887943268,
      0.2540999948978424,
      0.25849997997283936,
      0.2540000081062317,
      0.2516999840736389,
      0.25509998202323914,
      0.25110000371932983
    ],
    "model_name": "convnet"
  },
  "setting_14": {
    "batch_size": 512.0,
    "microbatch_size": 64,
    "test_batch_size": 1000,
    "iterations": 10000,
    "learning_rate": 0.025,
    "gamma": 0.9,
    "no_cuda": false,
    "dry_run": false,
    "seed": 1,
    "log_interval": 10,
    "save_model": false,
    "noise_multiplier": 2.0,
    "max_grad_norm": 0.72,
    "optimizer": "SGD",
    "enable_DP": true,
    "diminishing_gradient_norm": false,
    "is_individual_clipping": false,
    "data_sampling": "subsampling",
    "train_accuracy": [
      0.24526667594909668,
      0.24722222983837128,
      0.25157779455184937,
      0.2513555586338043,
      0.2522222101688385,
      0.25131112337112427,
      0.24977777898311615,
      0.2521333396434784,
      0.251244455575943,
      0.24924445152282715
    ],
    "test_accuracy": [
      0.25759997963905334,
      0.25589999556541443,
      0.25349998474121094,
      0.26080000400543213,
      0.2613999843597412,
      0.25609999895095825,
      0.25599998235702515,
      0.25519999861717224,
      0.251800000667572,
      0.25279998779296875
    ],
    "model_name": "convnet"
  },
  "setting_15": {
    "batch_size": 1024.0,
    "microbatch_size": 64,
    "test_batch_size": 1000,
    "iterations": 10000,
    "learning_rate": 0.025,
    "gamma": 0.9,
    "no_cuda": false,
    "dry_run": false,
    "seed": 1,
    "log_interval": 10,
    "save_model": false,
    "noise_multiplier": 2.0,
    "max_grad_norm": 0.72,
    "optimizer": "SGD",
    "enable_DP": true,
    "diminishing_gradient_norm": false,
    "is_individual_clipping": false,
    "data_sampling": "subsampling",
    "train_accuracy": [
      0.24693334102630615,
      0.24888889491558075,
      0.24871110916137695,
      0.250511109828949,
      0.25040000677108765,
      0.24951110780239105,
      0.25040000677108765,
      0.25055554509162903,
      0.25093334913253784,
      0.2511555552482605
    ],
    "test_accuracy": [
      0.26080000400543213,
      0.25540000200271606,
      0.2583000063896179,
      0.25119999051094055,
      0.258899986743927,
      0.26010000705718994,
      0.25200000405311584,
      0.25939998030662537,
      0.2583000063896179,
      0.2622999846935272
    ],
    "model_name": "convnet"
  },
  "setting_16": {
    "batch_size": 64.0,
    "microbatch_size": 64,
    "test_batch_size": 1000,
    "iterations": 10000,
    "learning_rate": 0.025,
    "gamma": 0.9,
    "no_cuda": false,
    "dry_run": false,
    "seed": 1,
    "log_interval": 10,
    "save_model": false,
    "noise_multiplier": 2.0,
    "max_grad_norm": 1.44,
    "optimizer": "SGD",
    "enable_DP": true,
    "diminishing_gradient_norm": false,
    "is_individual_clipping": false,
    "data_sampling": "subsampling",
    "train_accuracy": [
      0.2376222312450409,
      0.21066667139530182,
      0.22802221775054932,
      0.23075555264949799,
      0.2249777764081955,
      0.2110888957977295,
      0.2265111207962036,
      0.23968888819217682,
      0.23471111059188843,
      0.24524444341659546
    ],
    "test_accuracy": [
      0.2441999912261963,
      0.2117999941110611,
      0.2295999974012375,
      0.23330000042915344,
      0.22839999198913574,
      0.21089999377727509,
      0.2272999882698059,
      0.24859999120235443,
      0.24409998953342438,
      0.24390000104904175
    ],
    "model_name": "convnet"
  },
  "setting_17": {
    "batch_size": 128.0,
    "microbatch_size": 64,
    "test_batch_size": 1000,
    "iterations": 10000,
    "learning_rate": 0.025,
    "gamma": 0.9,
    "no_cuda": false,
    "dry_run": false,
    "seed": 1,
    "log_interval": 10,
    "save_model": false,
    "noise_multiplier": 2.0,
    "max_grad_norm": 1.44,
    "optimizer": "SGD",
    "enable_DP": true,
    "diminishing_gradient_norm": false,
    "is_individual_clipping": false,
    "data_sampling": "subsampling",
    "train_accuracy": [
      0.2530222237110138,
      0.2537555694580078,
      0.26177778840065,
      0.26448890566825867,
      0.2655777931213379,
      0.2768000066280365,
      0.26840001344680786,
      0.2641555666923523,
      0.26571112871170044,
      0.27124443650245667
    ],
    "test_accuracy": [
      0.2629999816417694,
      0.26159998774528503,
      0.25669997930526733,
      0.2669000029563904,
      0.2669000029563904,
      0.2751999795436859,
      0.26980000734329224,
      0.2719999849796295,
      0.2653000056743622,
      0.2726999819278717
    ],
    "model_name": "convnet"
  },
  "setting_18": {
    "batch_size": 256.0,
    "microbatch_size": 64,
    "test_batch_size": 1000,
    "iterations": 10000,
    "learning_rate": 0.025,
    "gamma": 0.9,
    "no_cuda": false,
    "dry_run": false,
    "seed": 1,
    "log_interval": 10,
    "save_model": false,
    "noise_multiplier": 2.0,
    "max_grad_norm": 1.44,
    "optimizer": "SGD",
    "enable_DP": true,
    "diminishing_gradient_norm": false,
    "is_individual_clipping": false,
    "data_sampling": "subsampling",
    "train_accuracy": [
      0.269222229719162,
      0.2683555483818054,
      0.26484444737434387,
      0.267977774143219,
      0.27317777276039124,
      0.2680000066757202,
      0.2658666670322418,
      0.2704888880252838,
      0.27104443311691284,
      0.275644451379776
    ],
    "test_accuracy": [
      0.2773999869823456,
      0.26980000734329224,
      0.26819998025894165,
      0.2766000032424927,
      0.27629998326301575,
      0.2815999984741211,
      0.27549999952316284,
      0.2782999873161316,
      0.27459999918937683,
      0.27300000190734863
    ],
    "model_name": "convnet"
  },
  "setting_19": {
    "batch_size": 512.0,
    "microbatch_size": 64,
    "test_batch_size": 1000,
    "iterations": 10000,
    "learning_rate": 0.025,
    "gamma": 0.9,
    "no_cuda": false,
    "dry_run": false,
    "seed": 1,
    "log_interval": 10,
    "save_model": false,
    "noise_multiplier": 2.0,
    "max_grad_norm": 1.44,
    "optimizer": "SGD",
    "enable_DP": true,
    "diminishing_gradient_norm": false,
    "is_individual_clipping": false,
    "data_sampling": "subsampling",
    "train_accuracy": [
      0.2781333327293396,
      0.27142223715782166,
      0.2758222222328186,
      0.2704666554927826,
      0.27079999446868896,
      0.2775999903678894,
      0.2728666663169861,
      0.2746666669845581,
      0.27115556597709656,
      0.2766000032424927
    ],
    "test_accuracy": [
      0.27469998598098755,
      0.27309998869895935,
      0.2735999822616577,
      0.27879998087882996,
      0.2782000005245209,
      0.27719998359680176,
      0.27219998836517334,
      0.27639999985694885,
      0.27539998292922974,
      0.2793000042438507
    ],
    "model_name": "convnet"
  },
  "setting_20": {
    "batch_size": 1024.0,
    "microbatch_size": 64,
    "test_batch_size": 1000,
    "iterations": 10000,
    "learning_rate": 0.025,
    "gamma": 0.9,
    "no_cuda": false,
    "dry_run": false,
    "seed": 1,
    "log_interval": 10,
    "save_model": false,
    "noise_multiplier": 2.0,
    "max_grad_norm": 1.44,
    "optimizer": "SGD",
    "enable_DP": true,
    "diminishing_gradient_norm": false,
    "is_individual_clipping": false,
    "data_sampling": "subsampling",
    "train_accuracy": [
      0.273844450712204,
      0.27522221207618713,
      0.27593332529067993,
      0.2758444547653198,
      0.2755555510520935,
      0.27408888936042786,
      0.2787555456161499,
      0.27506667375564575,
      0.2765111029148102,
      0.2774888873100281
    ],
    "test_accuracy": [
      0.2800000011920929,
      0.2784000039100647,
      0.28039997816085815,
      0.27730000019073486,
      0.27950000762939453,
      0.2833999991416931,
      0.27959999442100525,
      0.28049999475479126,
      0.2793000042438507,
      0.28369998931884766
    ],
    "model_name": "convnet"
  },
  "setting_21": {
    "batch_size": 64.0,
    "microbatch_size": 64,
    "test_batch_size": 1000,
    "iterations": 10000,
    "learning_rate": 0.025,
    "gamma": 0.9,
    "no_cuda": false,
    "dry_run": false,
    "seed": 1,
    "log_interval": 10,
    "save_model": false,
    "noise_multiplier": 2.0,
    "max_grad_norm": 2.88,
    "optimizer": "SGD",
    "enable_DP": true,
    "diminishing_gradient_norm": false,
    "is_individual_clipping": false,
    "data_sampling": "subsampling",
    "train_accuracy": [
      0.17820000648498535,
      0.19857777655124664,
      0.18575555086135864,
      0.20297777652740479,
      0.1982666701078415,
      0.15975555777549744,
      0.22537778317928314,
      0.19868889451026917,
      0.20608888566493988,
      0.20342221856117249
    ],
    "test_accuracy": [
      0.1850999891757965,
      0.19709999859333038,
      0.1842999905347824,
      0.20789998769760132,
      0.19909998774528503,
      0.16619999706745148,
      0.2298000007867813,
      0.20340000092983246,
      0.20349998772144318,
      0.21389999985694885
    ],
    "model_name": "convnet"
  },
  "setting_22": {
    "batch_size": 128.0,
    "microbatch_size": 64,
    "test_batch_size": 1000,
    "iterations": 10000,
    "learning_rate": 0.025,
    "gamma": 0.9,
    "no_cuda": false,
    "dry_run": false,
    "seed": 1,
    "log_interval": 10,
    "save_model": false,
    "noise_multiplier": 2.0,
    "max_grad_norm": 2.88,
    "optimizer": "SGD",
    "enable_DP": true,
    "diminishing_gradient_norm": false,
    "is_individual_clipping": false,
    "data_sampling": "subsampling",
    "train_accuracy": [
      0.21524444222450256,
      0.230244442820549,
      0.24913333356380463,
      0.2521555721759796,
      0.24240000545978546,
      0.24668888747692108,
      0.25519999861717224,
      0.2559777796268463,
      0.2567777931690216,
      0.2567777931690216
    ],
    "test_accuracy": [
      0.22039999067783356,
      0.2386999875307083,
      0.25540000200271606,
      0.25529998540878296,
      0.24619999527931213,
      0.251800000667572,
      0.26170000433921814,
      0.2563000023365021,
      0.2604999840259552,
      0.2653999924659729
    ],
    "model_name": "convnet"
  },
  "setting_23": {
    "batch_size": 256.0,
    "microbatch_size": 64,
    "test_batch_size": 1000,
    "iterations": 10000,
    "learning_rate": 0.025,
    "gamma": 0.9,
    "no_cuda": false,
    "dry_run": false,
    "seed": 1,
    "log_interval": 10,
    "save_model": false,
    "noise_multiplier": 2.0,
    "max_grad_norm": 2.88,
    "optimizer": "SGD",
    "enable_DP": true,
    "diminishing_gradient_norm": false,
    "is_individual_clipping": false,
    "data_sampling": "subsampling",
    "train_accuracy": [
      0.2634222209453583,
      0.26820001006126404,
      0.2645777761936188,
      0.2655111253261566,
      0.2742222249507904,
      0.27657777070999146,
      0.2756222188472748,
      0.2733111083507538,
      0.2748444378376007,
      0.2771555483341217
    ],
    "test_accuracy": [
      0.26479998230934143,
      0.26440000534057617,
      0.27129998803138733,
      0.2611999809741974,
      0.27219998836517334,
      0.27889999747276306,
      0.2750999927520752,
      0.27160000801086426,
      0.27570000290870667,
      0.2750000059604645
    ],
    "model_name": "convnet"
  },
  "setting_24": {
    "batch_size": 512.0,
    "microbatch_size": 64,
    "test_batch_size": 1000,
    "iterations": 10000,
    "learning_rate": 0.025,
    "gamma": 0.9,
    "no_cuda": false,
    "dry_run": false,
    "seed": 1,
    "log_interval": 10,
    "save_model": false,
    "noise_multiplier": 2.0,
    "max_grad_norm": 2.88,
    "optimizer": "SGD",
    "enable_DP": true,
    "diminishing_gradient_norm": false,
    "is_individual_clipping": false,
    "data_sampling": "subsampling",
    "train_accuracy": [
      0.27364444732666016,
      0.27462223172187805,
      0.27702221274375916,
      0.27533334493637085,
      0.27444446086883545,
      0.27757778763771057,
      0.2808000147342682,
      0.2768666744232178,
      0.27524444460868835,
      0.2808888852596283
    ],
    "test_accuracy": [
      0.27709999680519104,
      0.2793999910354614,
      0.27709999680519104,
      0.2786000072956085,
      0.2863999903202057,
      0.2839999794960022,
      0.2809000015258789,
      0.2802000045776367,
      0.2816999852657318,
      0.28290000557899475
    ],
    "model_name": "convnet"
  },
  "setting_25": {
    "batch_size": 1024.0,
    "microbatch_size": 64,
    "test_batch_size": 1000,
    "iterations": 10000,
    "learning_rate": 0.025,
    "gamma": 0.9,
    "no_cuda": false,
    "dry_run": false,
    "seed": 1,
    "log_interval": 10,
    "save_model": false,
    "noise_multiplier": 2.0,
    "max_grad_norm": 2.88,
    "optimizer": "SGD",
    "enable_DP": true,
    "diminishing_gradient_norm": false,
    "is_individual_clipping": false,
    "data_sampling": "subsampling",
    "train_accuracy": [
      0.28415554761886597,
      0.2857777774333954,
      0.2818666696548462,
      0.2844444513320923,
      0.2842000126838684,
      0.28279998898506165,
      0.28291112184524536,
      0.28377777338027954,
      0.28324446082115173,
      0.2837555706501007
    ],
    "test_accuracy": [
      0.28360000252723694,
      0.28209999203681946,
      0.2865999937057495,
      0.28949999809265137,
      0.27869999408721924,
      0.28529998660087585,
      0.2872999906539917,
      0.284199982881546,
      0.2800000011920929,
      0.2857999801635742
    ],
    "model_name": "convnet"
  },
  "setting_26": {
    "batch_size": 64.0,
    "microbatch_size": 64,
    "test_batch_size": 1000,
    "iterations": 10000,
    "learning_rate": 0.025,
    "gamma": 0.9,
    "no_cuda": false,
    "dry_run": false,
    "seed": 1,
    "log_interval": 10,
    "save_model": false,
    "noise_multiplier": 2.0,
    "max_grad_norm": 5.76,
    "optimizer": "SGD",
    "enable_DP": true,
    "diminishing_gradient_norm": false,
    "is_individual_clipping": false,
    "data_sampling": "subsampling",
    "train_accuracy": [
      0.11964444816112518,
      0.13928888738155365,
      0.15053333342075348,
      0.13777777552604675,
      0.15760000050067902,
      0.17366667091846466,
      0.13144443929195404,
      0.15386666357517242,
      0.13771110773086548,
      0.16673333942890167
    ],
    "test_accuracy": [
      0.12520000338554382,
      0.140299990773201,
      0.1574999988079071,
      0.14419999718666077,
      0.16019999980926514,
      0.17489999532699585,
      0.13699999451637268,
      0.15209999680519104,
      0.1444000005722046,
      0.17299999296665192
    ],
    "model_name": "convnet"
  },
  "setting_27": {
    "batch_size": 128.0,
    "microbatch_size": 64,
    "test_batch_size": 1000,
    "iterations": 10000,
    "learning_rate": 0.025,
    "gamma": 0.9,
    "no_cuda": false,
    "dry_run": false,
    "seed": 1,
    "log_interval": 10,
    "save_model": false,
    "noise_multiplier": 2.0,
    "max_grad_norm": 5.76,
    "optimizer": "SGD",
    "enable_DP": true,
    "diminishing_gradient_norm": false,
    "is_individual_clipping": false,
    "data_sampling": "subsampling",
    "train_accuracy": [
      0.16962222754955292,
      0.1704888939857483,
      0.17268888652324677,
      0.18895556032657623,
      0.19804444909095764,
      0.19455555081367493,
      0.19900000095367432,
      0.20404444634914398,
      0.1975555568933487,
      0.19893333315849304
    ],
    "test_accuracy": [
      0.17979998886585236,
      0.1703999936580658,
      0.17880000174045563,
      0.1973000019788742,
      0.20189999043941498,
      0.1947999894618988,
      0.20260000228881836,
      0.20170000195503235,
      0.19839999079704285,
      0.1955999881029129
    ],
    "model_name": "convnet"
  },
  "setting_28": {
    "batch_size": 256.0,
    "microbatch_size": 64,
    "test_batch_size": 1000,
    "iterations": 10000,
    "learning_rate": 0.025,
    "gamma": 0.9,
    "no_cuda": false,
    "dry_run": false,
    "seed": 1,
    "log_interval": 10,
    "save_model": false,
    "noise_multiplier": 2.0,
    "max_grad_norm": 5.76,
    "optimizer": "SGD",
    "enable_DP": true,
    "diminishing_gradient_norm": false,
    "is_individual_clipping": false,
    "data_sampling": "subsampling",
    "train_accuracy": [
      0.20324444770812988,
      0.20375555753707886,
      0.20813333988189697,
      0.20484444499015808,
      0.20766666531562805,
      0.2046888917684555,
      0.2054888904094696,
      0.21095556020736694,
      0.21373333036899567,
      0.21466666460037231
    ],
    "test_accuracy": [
      0.20109999179840088,
      0.20309999585151672,
      0.20399999618530273,
      0.19900000095367432,
      0.20260000228881836,
      0.2093999981880188,
      0.20109999179840088,
      0.20979999005794525,
      0.21319998800754547,
      0.2029999941587448
    ],
    "model_name": "convnet"
  },
  "setting_29": {
    "batch_size": 512.0,
    "microbatch_size": 64,
    "test_batch_size": 1000,
    "iterations": 10000,
    "learning_rate": 0.025,
    "gamma": 0.9,
    "no_cuda": false,
    "dry_run": false,
    "seed": 1,
    "log_interval": 10,
    "save_model": false,
    "noise_multiplier": 2.0,
    "max_grad_norm": 5.76,
    "optimizer": "SGD",
    "enable_DP": true,
    "diminishing_gradient_norm": false,
    "is_individual_clipping": false,
    "data_sampling": "subsampling",
    "train_accuracy": [
      0.21595555543899536,
      0.21506667137145996,
      0.21611110866069794,
      0.21673333644866943,
      0.22055555880069733,
      0.2184000015258789,
      0.21817778050899506,
      0.2202666699886322,
      0.223288893699646,
      0.22351111471652985
    ],
    "test_accuracy": [
      0.21389999985694885,
      0.21369999647140503,
      0.21869999170303345,
      0.2175999879837036,
      0.2199999988079071,
      0.2214999943971634,
      0.2240999937057495,
      0.21949999034404755,
      0.21949999034404755,
      0.2184000015258789
    ],
    "model_name": "convnet"
  },
  "setting_30": {
    "batch_size": 1024.0,
    "microbatch_size": 64,
    "test_batch_size": 1000,
    "iterations": 10000,
    "learning_rate": 0.025,
    "gamma": 0.9,
    "no_cuda": false,
    "dry_run": false,
    "seed": 1,
    "log_interval": 10,
    "save_model": false,
    "noise_multiplier": 2.0,
    "max_grad_norm": 5.76,
    "optimizer": "SGD",
    "enable_DP": true,
    "diminishing_gradient_norm": false,
    "is_individual_clipping": false,
    "data_sampling": "subsampling",
    "train_accuracy": [
      0.21784444153308868,
      0.22473333775997162,
      0.2262222319841385,
      0.2272000014781952,
      0.22255556285381317,
      0.227377787232399,
      0.22802221775054932,
      0.22528889775276184,
      0.22466666996479034,
      0.22673334181308746
    ],
    "test_accuracy": [
      0.2158999890089035,
      0.22100000083446503,
      0.22669999301433563,
      0.22169999778270721,
      0.2345999926328659,
      0.22609999775886536,
      0.2304999977350235,
      0.22450000047683716,
      0.2298000007867813,
      0.22669999301433563
    ],
    "model_name": "convnet"
  },
  "setting_31": {
    "batch_size": 1024.0,
    "microbatch_size": 64,
    "test_batch_size": 1000,
    "iterations": 10000,
    "learning_rate": 0.025,
    "gamma": 0.9,
    "no_cuda": false,
    "dry_run": false,
    "seed": 1,
    "log_interval": 10,
    "save_model": false,
    "noise_multiplier": 2.0,
    "max_grad_norm": 5.76,
    "optimizer": "SGD",
    "enable_DP": true,
    "diminishing_gradient_norm": false,
    "is_individual_clipping": false,
    "data_sampling": "subsampling",
    "train_accuracy": [
      0.22468888759613037,
      0.227911114692688,
      0.22555555403232574,
      0.22788889706134796,
      0.2295999974012375,
      0.22686666250228882,
      0.2285555601119995,
      0.22706666588783264,
      0.22397777438163757,
      0.23144444823265076
    ],
    "test_accuracy": [
      0.2230999916791916,
      0.23259998857975006,
      0.22749999165534973,
      0.23489999771118164,
      0.2295999974012375,
      0.22739998996257782,
      0.22659999132156372,
      0.23029999434947968,
      0.21969999372959137,
      0.23070000112056732
    ],
    "model_name": "convnet"
  }
}